aiohypixel/__init__.py
aiohypixel/__main__.py
aiohypixel/boosters.py
aiohypixel/friends.py
aiohypixel/guild.py
aiohypixel/keys.py
aiohypixel/leaderboards.py
aiohypixel/player.py
aiohypixel/resources/__init__.py
aiohypixel/resources/achievements.py
aiohypixel/resources/challenges.py
aiohypixel/resources/guilds.py
aiohypixel/resources/quests.py
aiohypixel/resources/skyblock.py
aiohypixel/session.py
aiohypixel/shared.py
aiohypixel/skyblock.py
aiohypixel/stats.py
aiohypixel/watchdogstats.py
aiohypixel-0.2.1.dist-info/WHEEL
aiohypixel-0.2.1.dist-info/METADATA
aiohypixel-0.2.1.dist-info/RECORD
